marimo_notebook/admin_console.py
marimo_notebook/run.sh
marimo_notebook-1.0.0.dist-info/LICENSE.txt
marimo_notebook-1.0.0.dist-info/METADATA
marimo_notebook-1.0.0.dist-info/WHEEL
marimo_notebook-1.0.0.dist-info/RECORD
